couchbase_haystack/__init__.py
couchbase_haystack/components/retrievers/__init__.py
couchbase_haystack/components/retrievers/embedding_retriever.py
couchbase_haystack/document_stores/__init__.py
couchbase_haystack/document_stores/auth.py
couchbase_haystack/document_stores/cluster_options.py
couchbase_haystack/document_stores/document_store.py
couchbase_haystack/document_stores/filters.py
couchbase_haystack-2.0.0.dist-info/METADATA
couchbase_haystack-2.0.0.dist-info/WHEEL
couchbase_haystack-2.0.0.dist-info/licenses/LICENSE
couchbase_haystack-2.0.0.dist-info/RECORD
