Metadata-Version: 2.4
Name: couchbase-haystack
Version: 2.0.0
Summary: Couchbase haystack integration
Project-URL: Documentation, https://github.com/Couchbase-Ecosystem/couchbase-haystack#readme
Project-URL: Issues, https://github.com/Couchbase-Ecosystem/couchbase-haystack/issues
Project-URL: Source, https://github.com/Couchbase-Ecosystem/couchbase-haystack
Author-email: Shyam Venkat <shyam.venkat@couchbase.com>
License-Expression: MIT
License-File: LICENSE
Classifier: Development Status :: 4 - Beta
Classifier: Programming Language :: Python
Classifier: Programming Language :: Python :: 3.8
Classifier: Programming Language :: Python :: 3.9
Classifier: Programming Language :: Python :: 3.10
Classifier: Programming Language :: Python :: 3.11
Classifier: Programming Language :: Python :: 3.12
Classifier: Programming Language :: Python :: Implementation :: CPython
Classifier: Programming Language :: Python :: Implementation :: PyPy
Requires-Python: >=3.8
Requires-Dist: backports-datetime-fromisoformat
Requires-Dist: couchbase==4.*
Requires-Dist: haystack-ai>=2.3.0
